messages/__init__.py
messages/__main__.py
messages/cli.py
messages/contacts.py
messages/db.py
messages/models.py
messages/phone.py
macos_messages-0.2.0.dist-info/METADATA
macos_messages-0.2.0.dist-info/WHEEL
macos_messages-0.2.0.dist-info/entry_points.txt
macos_messages-0.2.0.dist-info/licenses/LICENSE
macos_messages-0.2.0.dist-info/RECORD
