Metadata-Version: 2.4
Name: macos-messages
Version: 0.2.0
Summary: Python library and CLI for reading macOS Messages.app data
Project-URL: Homepage, https://github.com/tpritc/macos-messages
Project-URL: Documentation, https://macos-messages.readthedocs.io
Project-URL: Issues, https://github.com/tpritc/macos-messages/issues
Author-email: Tom Pritchard <tom@tpritc.com>
License-Expression: MIT
License-File: LICENSE
Keywords: chat,imessage,macos,messages,rcs,sms,sqlite
Classifier: Development Status :: 3 - Alpha
Classifier: Environment :: Console
Classifier: Environment :: MacOS X
Classifier: Intended Audience :: Developers
Classifier: License :: OSI Approved :: MIT License
Classifier: Operating System :: MacOS
Classifier: Programming Language :: Python :: 3
Classifier: Programming Language :: Python :: 3.12
Classifier: Programming Language :: Python :: 3.13
Classifier: Topic :: Communications :: Chat
Requires-Python: >=3.12
Requires-Dist: click>=8.0
Requires-Dist: phonenumbers>=8.13
Provides-Extra: docs
Requires-Dist: mkdocs-shadcn>=0.2; extra == 'docs'
Requires-Dist: mkdocs>=1.6; extra == 'docs'
Requires-Dist: pymdown-extensions>=10.0; extra == 'docs'
